openpromptu/__init__.py
openpromptu/data_utils.py
openpromptu/manual_template.py
openpromptu/tokenizer_wrapper.py
openpromptu/prompts/__init__.py
openpromptu/prompts/generation_verbalizer.py
openpromptu/prompts/manual_template.py
openpromptu/prompts/manual_verbalizer.py
openpromptu/utils/__init__.py
openpromptu/utils/logging.py
openpromptu-0.1.0.dist-info/METADATA
openpromptu-0.1.0.dist-info/WHEEL
openpromptu-0.1.0.dist-info/top_level.txt
openpromptu-0.1.0.dist-info/RECORD
